kaen/__init__.py
kaen/main.py
kaen/osds.py
kaen/spark.py
kaen/torch.py
kaen/hpo/__init__.py
kaen/hpo/client.py
kaen/hpo/examples.py
kaen/hpo/mlflow.py
kaen/hpo/mlflow_utils.py
kaen/hpo/optuna.py
kaen/hpo/services.py
kaen-1.0.1.31.dist-info/METADATA
kaen-1.0.1.31.dist-info/WHEEL
kaen-1.0.1.31.dist-info/entry_points.txt
kaen-1.0.1.31.dist-info/top_level.txt
kaen-1.0.1.31.dist-info/RECORD
